{
  "status": "ok",
  "totalResults": 6212,
  "articles": [
    {
      "source": {
        "id": null,
        "name": "New York Times"
      },
      "author": "Victor Mather",
      "title": "Shane Warne, Cricket Legend, Dies at 52",
      "description": "Warne’s management company said the Australian star died Friday of a suspected heart attack.",
      "url": "https://www.nytimes.com/2022/03/04/sports/cricket/shane-warne-dead.html",
      "urlToImage": "https://static01.nyt.com/images/2022/03/04/sports/04warneWEB1/merlin_203223255_e7279261-1f33-4aa8-97a8-5401c95fb72e-facebookJumbo.jpg",
      "publishedAt": "2022-03-04T18:10:41Z",
      "content": "Shane Warne, one of the greatest cricket players of all time, and a larger-than-life figure on and off the field, died Friday in Thailand. He was 52.\r\nThe cause was suspected to be a heart attack, hi… [+927 chars]"
    },
    {
      "source": {
        "id": "bbc-news",
        "name": "BBC News"
      },
      "author": null,
      "title": "Australian cricket legend Warne dies aged 52",
      "description": "Legendary Australia leg-spinner Shane Warne, one of the greatest cricketers of all time, dies of a suspected heart attack aged 52.",
      "url": "https://www.bbc.co.uk/sport/cricket/60622426",
      "urlToImage": "https://ichef.bbci.co.uk/live-experience/cps/624/cpsprodpb/13590/production/_97584297_breaking_news.png",
      "publishedAt": "2022-03-04T14:27:53Z",
      "content": "Legendary Australia leg-spinner Shane Warne, one of the greatest cricketers of all time, has died of a suspected heart attack aged 52.\r\nWarne took 708 Test wickets, the second most of all time, in 14… [+284 chars]"
    },
    {
      "source": {
        "id": "bbc-news",
        "name": "BBC News"
      },
      "author": "https://www.facebook.com/bbcnews",
      "title": "Shane Warne: Australian cricket legend died from natural causes - police",
      "description": "Thai police say there's no sign of foul play in the cricketer's death while on holiday on Koh Samui.",
      "url": "https://www.bbc.co.uk/news/world-asia-60645939",
      "urlToImage": "https://ichef.bbci.co.uk/news/1024/branded_news/108B7/production/_123576776_mediaitem123576775.jpg",
      "publishedAt": "2022-03-07T09:23:35Z",
      "content": "Image caption, Warne had been on holiday on Koh Samui when he died of a suspected heart attack\r\nAustralian cricket legend Shane Warne's death in Thailand was from natural causes, police have confirme… [+449 chars]"
    },
    {
      "source": {
        "id": "bbc-news",
        "name": "BBC News"
      },
      "author": "https://www.facebook.com/bbcnews",
      "title": "Women's World Cup: An India v Pakistan cricket match minus fireworks",
      "description": "The arch rivals face each other on Sunday in the Women's ODI cricket World Cup in New Zealand.",
      "url": "https://www.bbc.co.uk/news/world-asia-india-60572874",
      "urlToImage": "https://ichef.bbci.co.uk/news/1024/branded_news/5769/production/_123477322_gettyimages-805583774-594x594.jpg",
      "publishedAt": "2022-03-05T01:29:12Z",
      "content": "Image source, Getty Images\r\nImage caption, India's star batter Smriti Mandhana has recovered from a blow on her helmet in a warm-up game\r\nArch rivals India and Pakistan will face each other in a marq… [+5340 chars]"
    },
    {
      "source": {
        "id": "bbc-news",
        "name": "BBC News"
      },
      "author": null,
      "title": "South Africa survive to beat Pakistan at Women's Cricket World Cup",
      "description": "South Africa survive to beat Pakistan by six runs in another thrilling finish at the Women's Cricket World Cup.",
      "url": "https://www.bbc.co.uk/sport/cricket/60673994",
      "urlToImage": "https://ichef.bbci.co.uk/live-experience/cps/624/cpsprodpb/FA50/production/_123608046_southafricacelebrate.jpg",
      "publishedAt": "2022-03-11T08:09:01Z",
      "content": "South Africa have won both of their games at the Women's Cricket World Cup\r\n<table><tr><th>Women's World Cup, Tauranga</th></tr>\r\n<tr><td>South Africa 223-9 (50 overs): Wolvaardt 75, Luus 62</td></tr… [+658 chars]"
    },
    {
      "source": {
        "id": "bbc-news",
        "name": "BBC News"
      },
      "author": null,
      "title": "Small change will not make the difference English cricket needs, says Strauss",
      "description": "Sir Andrew Strauss warns that English cricket may need more than just incremental change if it wants to produce a quality men's Test team.",
      "url": "https://www.bbc.co.uk/sport/cricket/60741103",
      "urlToImage": "https://ichef.bbci.co.uk/live-experience/cps/624/cpsprodpb/D4E4/production/_123700545_gettyimages-1385156497.jpg",
      "publishedAt": "2022-03-14T18:20:20Z",
      "content": "'We don't have a moment to lose' - Strauss on review of domestic cricket\r\nSir Andrew Strauss has warned that English cricket may need more than just incremental change if it wants to produce a qualit… [+4722 chars]"
    },
    {
      "source": {
        "id": null,
        "name": "New York Times"
      },
      "author": "Rory Smith",
      "title": "Roman Abramovich and the End of Soccer’s Oligarch Era",
      "description": "Stripped of its Russian benefactor, Chelsea now faces a reckoning. Soccer’s will come next.",
      "url": "https://www.nytimes.com/2022/03/11/sports/soccer/roman-abramovich-chelsea.html",
      "urlToImage": "https://static01.nyt.com/images/2022/03/11/multimedia/11rory-roman2/11rory-roman2-facebookJumbo.jpg",
      "publishedAt": "2022-03-11T16:00:07Z",
      "content": "We would be here for a long time if I listed every single Brooklynite who wrote in, last week, to inform me that there are, as it happens, several cricket grounds in Brooklyn. There are so many, in f… [+976 chars]"
    },
    {
      "source": {
        "id": "bbc-news",
        "name": "BBC News"
      },
      "author": null,
      "title": "England looking to defend trophy with Women's Cricket World Cup set to begin",
      "description": "The Women's Cricket World Cup in New Zealand gets under way on Friday, with England looking to defend the trophy they won in 2017.",
      "url": "https://www.bbc.co.uk/sport/cricket/60583044",
      "urlToImage": "https://ichef.bbci.co.uk/live-experience/cps/624/cpsprodpb/CFA5/production/_123475135_worldcupsplit.jpg",
      "publishedAt": "2022-03-03T06:48:09Z",
      "content": "Eight teams are taking part in the Women's Cricket World Cup\r\n<table><tr><th>ICC Women's World Cup 2022</th></tr>\r\n<tr><td>Hosts: New Zealand (six venues) Dates: 4 March - 3 April</td></tr><tr><td>BB… [+5566 chars]"
    },
    {
      "source": {
        "id": "bbc-news",
        "name": "BBC News"
      },
      "author": null,
      "title": "Cummins, Root & Strauss lead tributes paid to 'greatest showman' Warne",
      "description": "Australia Test captain Pat Cummins calls Shane Warne a \"once-in-a-century cricketer\" as he leads tributes to the iconic leg-spinner who died on Friday aged 52.",
      "url": "https://www.bbc.co.uk/sport/cricket/60626656",
      "urlToImage": "https://ichef.bbci.co.uk/live-experience/cps/624/cpsprodpb/AEB3/production/_123532744_gettyimages-53352186.jpg",
      "publishedAt": "2022-03-04T20:52:16Z",
      "content": "Shane Warne: Pat Cummins pays tribute to 'all-time great'\r\nAustralia Test captain Pat Cummins says Shane Warne was a \"once-in-a-century cricketer\" as he led the tributes to the iconic leg-spinner who… [+4210 chars]"
    },
    {
      "source": {
        "id": "bbc-news",
        "name": "BBC News"
      },
      "author": null,
      "title": "Meg Lanning: Australia's captain desperate for World Cup success",
      "description": "She is the best player in possibly the best international sports side in the world - but who is the real Meg Lanning?",
      "url": "https://www.bbc.co.uk/sport/cricket/60892215",
      "urlToImage": "https://ichef.bbci.co.uk/live-experience/cps/624/cpsprodpb/34F9/production/_123916531_lanningindex.png",
      "publishedAt": "2022-03-29T05:36:36Z",
      "content": "Meg Lanning has won more than 200 caps for Australia\r\n<table><tr><th>ICC Women's World Cup semi-final: Australia v West Indies</th></tr>\r\n<tr><td>Date: 29 March Time: 23:00 BST Venue: Basin Reserve, … [+6695 chars]"
    },
    {
      "source": {
        "id": "bbc-news",
        "name": "BBC News"
      },
      "author": "https://www.facebook.com/bbcnews",
      "title": "Shane Warne: Hurley pays tribute to 'beloved lionheart'",
      "description": "Elizabeth Hurley remembers her former fiance as her son Damian describes him as a father figure.",
      "url": "https://www.bbc.co.uk/news/uk-60634012",
      "urlToImage": "https://ichef.bbci.co.uk/news/1024/branded_news/2F98/production/_123548121_gettyimages-131212973-1.jpg",
      "publishedAt": "2022-03-05T17:30:04Z",
      "content": "Image source, Getty Images\r\nElizabeth Hurley has paid tribute to former fiance Shane Warne as her \"beloved lionheart\", after the cricket legend's death aged 52.\r\nThe model and actress posted a series… [+997 chars]"
    },
    {
      "source": {
        "id": "reuters",
        "name": "Reuters"
      },
      "author": null,
      "title": "West Indies cricket \"pioneer\" Ramadhin dies aged 92 - Reuters",
      "description": "Former test spinner Sonny Ramadhin, a key part of the West Indies side that won a first away series in England in 1950 and described as \"pioneer\" of the game, has died aged 92, officials said.",
      "url": "https://www.reuters.com/lifestyle/sports/west-indies-cricket-pioneer-ramadhin-dies-aged-92-2022-02-27/",
      "urlToImage": "https://www.reuters.com/pf/resources/images/reuters/reuters-default.png?d=75",
      "publishedAt": "2022-02-27T22:08:00Z",
      "content": "Feb 27 (Reuters) - Former test spinner Sonny Ramadhin, a key part of the West Indies side that won a first away series in England in 1950 and described as \"pioneer\" of the game, has died aged 92, off… [+1107 chars]"
    },
    {
      "source": {
        "id": "reuters",
        "name": "Reuters"
      },
      "author": null,
      "title": "Disney without cricket risks its streaming game - Reuters",
      "description": "Cricket has been a magic wand for Walt Disney <a href=\"https://www.reuters.com/companies/DIS.N\" target=\"_blank\">(DIS.N)</a> in India. The $270 billion entertainment giant holds the exclusive rights for lucrative Indian Premier League cricket, but these are no…",
      "url": "https://www.reuters.com/markets/asia/disney-without-cricket-risks-its-streaming-game-2022-03-03/",
      "urlToImage": "https://www.reuters.com/pf/resources/images/reuters/reuters-default.png?d=77",
      "publishedAt": "2022-03-03T15:29:00Z",
      "content": "NEW YORK, March 3 (Reuters Breakingviews) - Cricket has been a magic wand for Walt Disney (DIS.N) in India. The $270 billion entertainment giant holds the exclusive rights for lucrative Indian Premie… [+3897 chars]"
    },
    {
      "source": {
        "id": "reuters",
        "name": "Reuters"
      },
      "author": null,
      "title": "Rafiq fears he may never work again after speaking out about racism - Reuters.com",
      "description": "Former Yorkshire spinner Azeem Rafiq fears speaking out about racism in English cricket has made him unemployable.",
      "url": "https://www.reuters.com/lifestyle/sports/rafiq-fears-he-may-never-work-again-after-speaking-out-about-racism-2022-03-08/",
      "urlToImage": "https://www.reuters.com/resizer/xtwFIVcWEkfcQnBAOQAShEg1vuA=/1200x628/smart/filters:quality(80)/cloudfront-us-east-2.images.arcpublishing.com/reuters/QAAPZZI3DZKOVP2YT6ANZGUNLE.jpg",
      "publishedAt": "2022-03-08T17:44:00Z",
      "content": "March 8 (Reuters) - Former Yorkshire spinner Azeem Rafiq fears speaking out about racism in English cricket has made him unemployable.\r\nRafiq, who is of Pakistani descent, told a British parliamentar… [+2108 chars]"
    },
    {
      "source": {
        "id": "reuters",
        "name": "Reuters"
      },
      "author": null,
      "title": "Pakistan, Australia vie for series win as test returns to Lahore - Reuters.com",
      "description": "Pakistan and Australia head into a winner-take-all third and final test from Monday as test cricket returns to Lahore's Gaddafi Stadium for the first time since the 2009 attack by gunmen on a bus carrying the Sri Lankan cricket team. (For a FACTBOX on the mat…",
      "url": "https://www.reuters.com/lifestyle/sports/pakistan-australia-vie-series-win-test-returns-lahore-2022-03-20/",
      "urlToImage": "https://www.reuters.com/resizer/uFoxVuyCIZHd4cn9k1Vx0l3RBSY=/1200x628/smart/filters:quality(80)/cloudfront-us-east-2.images.arcpublishing.com/reuters/UPRO73SNUZOB3BJ6JKFVGMARMY.jpg",
      "publishedAt": "2022-03-20T09:01:00Z",
      "content": "March 20 (Reuters) - Pakistan and Australia head into a winner-take-all third and final test from Monday as test cricket returns to Lahore's Gaddafi Stadium for the first time since the 2009 attack b… [+1978 chars]"
    },
    {
      "source": {
        "id": null,
        "name": "The Guardian"
      },
      "author": "Sean Ingle",
      "title": "Cricket faces discrimination ‘reckoning’, warns independent report chair",
      "description": "<ul><li>‘All is not well in cricket,’ warns ICEC chair Cindy Butts</li><li>More than 4,000 have shared experiences of discrimination</li></ul>Cricket is “facing a reckoning” as a result of the Azeem Rafiq affair and needs to take a long look in the mirror whe…",
      "url": "https://amp.theguardian.com/sport/2022/mar/10/cricket-is-facing-a-reckoning-chair-of-icec-says-major-change-needed",
      "urlToImage": "https://i.guim.co.uk/img/media/194f182cc68a1543a1bcc116d2ed584fc00de93e/0_180_3500_2100/master/3500.jpg?width=1200&height=630&quality=85&auto=format&fit=crop&overlay-align=bottom%2Cleft&overlay-width=100p&overlay-base64=L2ltZy9zdGF0aWMvb3ZlcmxheXMvdGctZGVmYXVsdC5wbmc&enable=upscale&s=37067ed510a705aee446fc7345eaeeef",
      "publishedAt": "2022-03-10T18:51:14Z",
      "content": "Cricket is facing a reckoning as a result of the Azeem Rafiq affair and needs to take a long look in the mirror when it comes to discrimination, the chair of the Independent Commission for Equity in … [+2240 chars]"
    },
    {
      "source": {
        "id": null,
        "name": "The Guardian"
      },
      "author": "Guardian sport",
      "title": "Rodney Marsh: Australian cricket great dies aged 74",
      "description": "The 96-Test former wicketkeeper was put in an induced coma after suffering a major heart attack last weekAustralian cricket great Rod Marsh has died, aged 74.The former wicketkeeper suffered a heart attack in Queensland last week and died in Adelaide on Frida…",
      "url": "https://amp.theguardian.com/sport/2022/mar/04/rodney-marsh-australian-cricket-great-dies-aged-74",
      "urlToImage": "https://i.guim.co.uk/img/media/3f1ef7803b00885a53798c2f7181d48e3c761421/0_1006_2710_1625/master/2710.jpg?width=1200&height=630&quality=85&auto=format&fit=crop&overlay-align=bottom%2Cleft&overlay-width=100p&overlay-base64=L2ltZy9zdGF0aWMvb3ZlcmxheXMvdGctZGVmYXVsdC5wbmc&enable=upscale&s=f7b973f22d8a37dc5b4b92051ab34d7a",
      "publishedAt": "2022-03-03T23:06:38Z",
      "content": "Australian cricket great Rod Marsh has died, aged 74.\r\nThe former wicketkeeper suffered a heart attack in Queensland last week and died in Adelaide on Friday.\r\nHe played the first of his 96 Tests for… [+830 chars]"
    },
    {
      "source": {
        "id": null,
        "name": "The Guardian"
      },
      "author": "Justine Smith",
      "title": "Asian cricketer was ‘silenced’ for criticising club’s blackface party",
      "description": "ECB to investigate as game risks losing generation of aspiring players over racismAn Asian cricketer claims he was subject to a disciplinary hearing after calling for an apology from a Leicestershire club whose members “blacked-up” for a fancy dress party. It…",
      "url": "https://amp.theguardian.com/world/2022/mar/27/asian-cricketer-was-silenced-for-criticising-clubs-blackface-party",
      "urlToImage": "https://i.guim.co.uk/img/media/11a5213431e76c967c8a106da2bff041c8dfd6bb/0_60_1080_648/master/1080.jpg?width=1200&height=630&quality=85&auto=format&fit=crop&overlay-align=bottom%2Cleft&overlay-width=100p&overlay-base64=L2ltZy9zdGF0aWMvb3ZlcmxheXMvdG8tZGVmYXVsdC5wbmc&enable=upscale&s=657c5a6987f52fa119e2128e9afee472",
      "publishedAt": "2022-03-27T06:45:18Z",
      "content": "An Asian cricketer claims he was subject to a disciplinary hearing after calling for an apology from a Leicestershire club whose members blacked-up for a fancy dress party. It is the latest incident … [+8095 chars]"
    },
    {
      "source": {
        "id": null,
        "name": "The Guardian"
      },
      "author": "Ali Martin in Grenada",
      "title": "Jason Roy fined and given suspended two-match ban for undisclosed reason",
      "description": "<ul><li>ECB declines to give further details of Roy’s alleged offence</li><li>Opener will take break from game to ‘spend time with family’</li></ul>Jason Roy has been hit with a suspended two-match ban from international cricket and a £2,500 fine, the reasons…",
      "url": "https://amp.theguardian.com/sport/2022/mar/22/jason-roy-fined-and-given-suspended-two-match-ban-for-undisclosed-reason",
      "urlToImage": "https://i.guim.co.uk/img/media/f6903053e04bd0b2ce0e0d89c380b48a6ce14092/0_46_1538_923/master/1538.jpg?width=1200&height=630&quality=85&auto=format&fit=crop&overlay-align=bottom%2Cleft&overlay-width=100p&overlay-base64=L2ltZy9zdGF0aWMvb3ZlcmxheXMvdGctZGVmYXVsdC5wbmc&enable=upscale&s=cf89c6977cf2fdd9ade4bad7c0cbf42a",
      "publishedAt": "2022-03-22T19:08:22Z",
      "content": "Jason Roy has been hit with a suspended two-match ban from international cricket and a £2,500 fine, the reasons for which are being kept out of the public domain by the England and Wales Cricket Boar… [+1984 chars]"
    },
    {
      "source": {
        "id": null,
        "name": "The Guardian"
      },
      "author": "Australian Associated Press",
      "title": "Shane Warne suffered chest pains before he travelled to Thailand, police say",
      "description": "Thai police said the cricket legend’s death on the island of Koh Samui is not being treated as suspicious<ul><li>Australian cricket legend dies aged 52</li><li>Cummins leads tributes to ‘a once-in-a-century cricketer’</li><li>Shane Warne: a life in pictures |…",
      "url": "https://amp.theguardian.com/sport/2022/mar/06/shane-warne-suffered-chest-pains-before-he-travelled-to-thailand-police-say",
      "urlToImage": "https://i.guim.co.uk/img/media/38b4e13dceaa887d2e55f61ebacdca1c12facd82/0_108_3459_2076/master/3459.jpg?width=1200&height=630&quality=85&auto=format&fit=crop&overlay-align=bottom%2Cleft&overlay-width=100p&overlay-base64=L2ltZy9zdGF0aWMvb3ZlcmxheXMvdGctZGVmYXVsdC5wbmc&enable=upscale&s=6f57d062a10481e28d7693762161b75c",
      "publishedAt": "2022-03-05T22:57:32Z",
      "content": "Shane Warne suffered chest pains before he travelled to Thailand for a holiday, where the cricket great died from a suspected heart attack on Friday, Thai police say.\r\nCiting information from his fam… [+1645 chars]"
    }
  ]
}
